value_iteration/Gridworld_Constructor.py
value_iteration/MDP.py
value_iteration/Markov_Decision_Process.py
value_iteration/__init__.py
value_iteration-1.0.1.dist-info/METADATA
value_iteration-1.0.1.dist-info/WHEEL
value_iteration-1.0.1.dist-info/top_level.txt
value_iteration-1.0.1.dist-info/RECORD
